gpush.py
gpush-3.1.2.data/scripts/_version.py
gpush-3.1.2.data/scripts/gpush
gpush-3.1.2.dist-info/LICENSE
gpush-3.1.2.dist-info/METADATA
gpush-3.1.2.dist-info/WHEEL
gpush-3.1.2.dist-info/top_level.txt
gpush-3.1.2.dist-info/RECORD
