Metadata-Version: 2.1
Name: gpush
Version: 3.1.2
License-File: LICENSE
Requires-Dist: gitpython (==3.1.31)
Requires-Dist: inquirer (==3.1.3)
Requires-Dist: python-gitlab (==3.13.0)
Requires-Dist: ghapi (==1.0.3)
Requires-Dist: pytest (==7.2.1)
